think_ai_cli/__init__.py
think_ai_cli/cli.py
think_ai_cli/core.py
think_ai_cli/core_annoy.py
think_ai_cli-0.2.0.dist-info/licenses/LICENSE
think_ai_cli-0.2.0.dist-info/METADATA
think_ai_cli-0.2.0.dist-info/WHEEL
think_ai_cli-0.2.0.dist-info/entry_points.txt
think_ai_cli-0.2.0.dist-info/top_level.txt
think_ai_cli-0.2.0.dist-info/RECORD
