Metadata-Version: 2.4
Name: think-ai-cli
Version: 0.2.0
Summary: AI-powered coding assistant with vector search - no compilation required
Home-page: https://github.com/champi-dev/think_ai
Author: Think AI
Author-email: Think AI <contact@think-ai.dev>
License: MIT
Project-URL: Homepage, https://github.com/champi-dev/think_ai
Project-URL: Bug Reports, https://github.com/champi-dev/think_ai/issues
Project-URL: Source, https://github.com/champi-dev/think_ai
Classifier: Development Status :: 4 - Beta
Classifier: Intended Audience :: Developers
Classifier: Topic :: Software Development :: Libraries :: Python Modules
Classifier: License :: OSI Approved :: MIT License
Classifier: Programming Language :: Python :: 3
Classifier: Programming Language :: Python :: 3.8
Classifier: Programming Language :: Python :: 3.9
Classifier: Programming Language :: Python :: 3.10
Classifier: Programming Language :: Python :: 3.11
Classifier: Programming Language :: Python :: 3.12
Classifier: Operating System :: OS Independent
Requires-Python: >=3.8
License-File: LICENSE
Requires-Dist: click>=8.0.0
Requires-Dist: rich>=13.0.0
Requires-Dist: annoy>=1.17.0
Requires-Dist: sentence-transformers>=2.0.0
Requires-Dist: requests>=2.25.0
Requires-Dist: pyyaml>=6.0
Requires-Dist: pygments>=2.10.0
Requires-Dist: torch>=2.0.0
Requires-Dist: numpy<2.0.0
Provides-Extra: dev
Requires-Dist: pytest>=7.0.0; extra == "dev"
Dynamic: author
Dynamic: home-page
Dynamic: license-file
Dynamic: requires-python
